LICENSE.txt
README.md
setup.cfg
setup.py
djangolazy/__init__.py
djangolazy/__main__.py
djangolazy/version.py
djangolazy.egg-info/PKG-INFO
djangolazy.egg-info/SOURCES.txt
djangolazy.egg-info/dependency_links.txt
djangolazy.egg-info/entry_points.txt
djangolazy.egg-info/not-zip-safe
djangolazy.egg-info/requires.txt
djangolazy.egg-info/top_level.txt